{
  "name": "voltz",
  "display_name": "Voltz",
  "url": "http://www.technicpack.net/voltz",
  "icon": "http://cdn.technicpack.net/resources/voltz/icon.png?1407499297",
  "icon_md5": "820ad79798bf8fce3317ad7bb6302384",
  "logo": "http://cdn.technicpack.net/resources/voltz/logo.png?1407499297",
  "logo_md5": "57bab00b470b738898084b29b541a3e7",
  "background": "http://cdn.technicpack.net/resources/voltz/background.png?1407499297",
  "background_md5": "e9111ee2909af2bc0fa78a50812b1c0a",
  "recommended": "2.0.4",
  "latest": "3.1.2",
  "builds": [
    "1.0.13",
    "1.0.12",
    "1.0.11",
    "1.0.10",
    "1.0.9",
    "1.0.8",
    "1.0.7",
    "1.0.6",
    "1.0.5",
    "1.0.4",
    "1.1.2",
    "1.1.3",
    "1.1.4",
    "2.0.1",
    "2.0.2",
    "2.0.4",
    "3.0.0",
    "3.0.0b",
    "v3.0.0c",
    "3.1.0",
    "3.1.1",
    "3.1.2"
  ]
}